auto_rxn/__init__.py
auto_rxn/__main__.py
auto_rxn/__version__.py
auto_rxn/_device.py
auto_rxn/_exceptions.py
auto_rxn/_limits.py
auto_rxn/_recipe.py
auto_rxn/_run.py
auto_rxn/_stage_unstage.py
auto_rxn/py.typed
auto_rxn/devices/__init__.py
auto_rxn/devices/_fake_furnace.py
auto_rxn/devices/_fake_mfc.py
auto_rxn/devices/_reading.py
auto_rxn/devices/_status.py
auto_rxn/testing/__init__.py
auto_rxn/testing/_with_happi_db.py
auto_rxn/testing/_with_limit_set_to.py
auto_rxn-2024.3.0.dist-info/METADATA
auto_rxn-2024.3.0.dist-info/WHEEL
auto_rxn-2024.3.0.dist-info/entry_points.txt
auto_rxn-2024.3.0.dist-info/licenses/LICENSE
auto_rxn-2024.3.0.dist-info/RECORD
