Metadata-Version: 2.3
Name: auto_rxn
Version: 2024.3.0
Project-URL: Source, https://github.com/uw-madison-chem-shops/auto_rxn
Project-URL: Issues, https://github.com/uw-madison-chem-shops/auto_rxn/issues
Project-URL: Home Page, https://uw-madison-chem-shops.github.io/auto_rxn/
License-Expression: MIT
License-File: LICENSE
Classifier: Development Status :: 4 - Beta
Classifier: Intended Audience :: Science/Research
Classifier: License :: OSI Approved :: MIT License
Classifier: Natural Language :: English
Classifier: Programming Language :: Python :: 3
Classifier: Programming Language :: Python :: 3.9
Classifier: Programming Language :: Python :: 3.10
Classifier: Programming Language :: Python :: 3.11
Classifier: Topic :: Scientific/Engineering
Requires-Python: >=3.9
Requires-Dist: bluesky
Requires-Dist: click
Requires-Dist: happi
Requires-Dist: pandas
Requires-Dist: platformdirs
Requires-Dist: suitcase-csv
Requires-Dist: tomli
Requires-Dist: tomli-w
Provides-Extra: dev
Requires-Dist: black; extra == 'dev'
Requires-Dist: pre-commit; extra == 'dev'
